{"run_number": "1735831917495850", "step_name": "save_results", "task_id": "5", "attempt_id": 0, "name": "data", "content_type": "gzip+pickle-v2", "type": "metaflow.artifact", "sha": "608f21357f2aebe74510dba7b544b398a528a18f", "ds_type": "local", "location": ":root:/Users/inandraashafardhana/Documents/kuliah/semester5/TugasUAS/.metaflow", "flow_id": "WhatsAppClusteringFlow", "user_name": "inandraashafardhana", "tags": [], "system_tags": ["python_version:3.13.0", "user:inandraashafardhana", "metaflow_version:2.13", "runtime:dev"], "ts_epoch": 1735831920770}